recallrate/__init__.py
recallrate/main_module.py
recallrate-1.0.dist-info/LICENSE
recallrate-1.0.dist-info/METADATA
recallrate-1.0.dist-info/WHEEL
recallrate-1.0.dist-info/top_level.txt
recallrate-1.0.dist-info/RECORD
